{
    "name": "Orthinanos",
    "description": "a redish discord theme that goes easy on your eyes!",
    "version": "1.0.3",
    "authors": [
       {
          "name": "Vortex",
          "id": "543174216493563925"
       }
    ],
    "theme_color_map": {
        "HEADER_PRIMARY": ["#e5b0b0","#FFFFFF"],
        "HEADER_SECONDARY": ["#895656","#FFFFFF"],
        "INTERACTIVE_ACTIVE": ["#e5b0b0","#FFFFFF"],
        "INTERACTIVE_MUTED": ["#d1b6b5","#FFFFFF"],
        "INTERACTIVE_NORMAL": ["#7c5d5d","#FFFFFF"],
        "CHANNELTEXTAREA_BACKGROUND": ["#211616","#FFFFFF"],
        "CHANNELS_DEFAULT": ["#f77979","#FFFFFF"],
"TEXT_DANGER": ["#895656","#FFFFFF"],
        "TEXT_NORMAL": ["#e5b0b0","#FFFFFF"],
        "TEXT_MUTED": ["#895656","#FFFFFF"],
        "TEXT_LINK": ["#f77979","#FFFFFF"],
            "KEYBOARD": ["#604242","#FFFFFF"],
        "BACKGROUND_PRIMARY": ["#261a1a","#FFFFFF"],
        "BACKGROUND_SECONDARY": ["#211616","#FFFFFF"],
        "BACKGROUND_SECONDARY_ALT": ["#191212","#FFFFFF"],
        "BACKGROUND_TERTIARY": ["#1e1616","#FFFFFF"],
        "BACKGROUND_ACCENT": ["#604242","#FFFFFF"],
        "BACKGROUND_FLOATING": ["#211616","#FFFFFF"],
        "BACKGROUND_NESTED_FLOATING": ["#211616","#FFFFFF"],
        "BACKGROUND_MOBILE_PRIMARY": ["#261a1a","#FFFFFF"],
        "BACKGROUND_MOBILE_SECONDARY": ["#211616","#FFFFFF"],
        "BACKGROUND_MODIFIER_HOVER": ["#302020","#FFFFFF"],
        "BACKGROUND_MODIFIER_ACTIVE": ["#352727","#FFFFFF"],
        "BACKGROUND_MODIFIER_SELECTED": ["#302323","#FFFFFF"],
        "BACKGROUND_MODIFIER_ACCENT": ["#281d1d","#FFFFFF"]
    },
    "unsafe_colors": {
        "CHAT_GREY": "#604242"
    },
    "colours": {
        "PRIMARY_DARK": "#b2b2b2",
        "PRIMARY_DARK_100": "#e5b0b0",
        "PRIMARY_DARK_200": "#e5b0b0",
        "PRIMARY_DARK_300": "#f77979",
        "PRIMARY_DARK_360": "#b2b2b2",
        "PRIMARY_DARK_400": "#f77979",
        "PRIMARY_DARK_500": "#352727",
        "PRIMARY_DARK_600": "#261a1a",
        "PRIMARY_DARK_630": "#261a1a",
        "PRIMARY_DARK_700": "#352727",
        "PRIMARY_DARK_800": "#261a1a",
        "PRIMARY_DARK_900": "#e5b0b0"
    }
}